win32_details/__init__.py
win32_details/cli.py
win32_details/win32_details.py
win32_details-0.5.0.dist-info/LICENSE
win32_details-0.5.0.dist-info/METADATA
win32_details-0.5.0.dist-info/WHEEL
win32_details-0.5.0.dist-info/entry_points.txt
win32_details-0.5.0.dist-info/top_level.txt
win32_details-0.5.0.dist-info/RECORD
