Metadata-Version: 2.1
Name: win32-details
Version: 0.5.0
Summary: .exe file details for your Nautilus file browser
Home-page: https://github.com/tfuxu/win32-details
Author: tfuxu
License: GPL-3.0
Project-URL: Bug Tracker, https://github.com/tfuxu/win32-details/issues
Project-URL: Source Code, https://github.com/tfuxu/win32-details
Keywords: nautilus extension exe details gnome
Platform: Linux
Platform: BSD
Classifier: Development Status :: 4 - Beta
Classifier: Environment :: X11 Applications :: Gnome
Classifier: License :: OSI Approved :: GNU General Public License v3 or later (GPLv3+)
Classifier: Operating System :: POSIX :: Linux
Classifier: Operating System :: POSIX :: BSD
Classifier: Programming Language :: Python
Classifier: Programming Language :: Python :: 3
Classifier: Programming Language :: Python :: 3 :: Only
Classifier: Programming Language :: Python :: 3.6
Classifier: Programming Language :: Python :: 3.7
Classifier: Programming Language :: Python :: 3.8
Classifier: Programming Language :: Python :: 3.9
Classifier: Programming Language :: Python :: 3.10
Classifier: Topic :: Utilities
Requires-Python: >=3.6
License-File: LICENSE
Requires-Dist: PyExifTool (>=0.5.2)
